raclients/__init__.py
raclients/auth.py
raclients/graph/__init__.py
raclients/graph/client.py
raclients/graph/transport.py
raclients/graph/util.py
raclients/modelclient/__init__.py
raclients/modelclient/base.py
raclients/modelclient/lora.py
raclients/modelclient/mo.py
raclients/py.typed
raclients/upload.py
raclients-3.3.5.dist-info/LICENSES/MPL-2.0.txt
raclients-3.3.5.dist-info/METADATA
raclients-3.3.5.dist-info/WHEEL
raclients-3.3.5.dist-info/RECORD
