Metadata-Version: 2.1
Name: raclients
Version: 3.3.5
Summary: Clients for OS2mo/LoRa
Home-page: https://magenta.dk/
License: MPL-2.0
Keywords: os2mo,lora
Author: Magenta
Author-email: info@magenta.dk
Requires-Python: >=3.10,<4.0
Classifier: License :: OSI Approved
Classifier: Programming Language :: Python :: 3
Classifier: Programming Language :: Python :: 3.10
Classifier: Programming Language :: Python :: 3.11
Classifier: Programming Language :: Python :: 3.12
Requires-Dist: Authlib (>=1.2.0,<2.0.0)
Requires-Dist: fastapi (>=0.88,<1.0)
Requires-Dist: gql (>=3.4.0,<4.0.0)
Requires-Dist: httpx (>=0.27.0,<0.28.0)
Requires-Dist: more-itertools (>=9.1.0,<10.0.0)
Requires-Dist: pydantic (>=1.10.5,<2.0.0)
Requires-Dist: ramodels (>=18.5.2,<23.0.0)
Requires-Dist: structlog (>=22.3,<24.0)
Requires-Dist: tenacity (>=8.2.2,<9.0.0)
Requires-Dist: tqdm (>=4.65.0,<5.0.0)
Project-URL: Repository, https://git.magenta.dk/rammearkitektur/ra-clients
